<?xml version="1.0" encoding="UTF-8"?>
<!-- Generated at Fri Oct 07 17:51:53 CEST 2016 from platform:/resource/org.occiware.clouddesigner.occi.docker/model/Docker.occie by org.occiware.clouddesigner.occi.gen.xml -->
<occi:extension xmlns:occi="http://schemas.ogf.org/occi"
    xmlns:xs="http://www.w3.org/2001/XMLSchema"
    xmlns:xsi="http://www.w3.org/2001/XMLSchema-instance"
    xsi:schemaLocation="http://schemas.ogf.org/occi occi.xsd"
    name="docker"
    scheme="http://occiware.org/occi/docker#"
    version="1"
    status="stable">

  <!-- Kind: Container Resource -->
  <occi:kind term="container" scheme="http://occiware.org/occi/docker#" title="Container Resource">
    <occi:parent term="compute" scheme="http://schemas.ogf.org/occi/infrastructure#"/>
    <occi:attribute name="name" use="required" type="xs:string" title="The name of this Container instance"/>
    <occi:attribute name="containerid" use="optional" type="xs:string" title="The ID of this Container instance"/>
    <occi:attribute name="image" use="optional" type="xs:string" title="The image of this Container instance"/>
    <occi:attribute name="build" use="optional" type="xs:string" title="The build directory of this Container instance"/>
    <occi:attribute name="command" use="optional" default="" type="xs:string" title="Override the default command in Dockerfile"/>
    <occi:attribute name="ports" use="optional" type="xs:string" title="The ports of this Container instance"/>
    <occi:attribute name="expose" use="optional" type="xs:string" title="The exposed ports of this Container instance"/>
    <occi:attribute name="volumes" use="optional" type="xs:string" title="The list of volumes"/>
    <occi:attribute name="environment" use="optional" type="xs:string" title="Environment variables"/>
    <occi:attribute name="env_file" use="optional" type="xs:string" title=""/>
    <occi:attribute name="net" use="optional" type="xs:string" title="&apos;bridge&apos;,  &apos;none&apos;, &apos;container:[name or id]&apos;, or &apos;host&apos;"/>
    <occi:attribute name="dns" use="optional" type="xs:string" title="Custom DNS servers"/>
    <occi:attribute name="dns_search" use="optional" type="xs:string" title="Custom DNS search domains"/>
    <occi:attribute name="cap_add" use="optional" type="xs:string" title="Add container capabilities"/>
    <occi:attribute name="cap_drop" use="optional" type="xs:string" title="Drop container capabilities"/>
    <occi:attribute name="working_dir" use="optional" type="xs:string" title="Working directory"/>
    <occi:attribute name="entrypoint" use="optional" type="xs:string" title="Entry point"/>
    <occi:attribute name="user" use="optional" type="xs:string" title=""/>
    <occi:attribute name="domainname" use="optional" type="xs:string" title=""/>
    <occi:attribute name="mem_limit" use="optional" type="xs:integer" title=""/>
    <occi:attribute name="memory_swap" use="optional" type="xs:integer" title="Memory swap limit"/>
    <occi:attribute name="privileged" use="optional" default="false" type="xs:boolean" title=""/>
    <occi:attribute name="restart" use="optional" default="" type="xs:string" title=""/>
    <occi:attribute name="stdin_open" use="optional" default="" type="xs:boolean" title=""/>
    <occi:attribute name="interactive" use="required" default="false" type="xs:boolean" title=""/>
    <occi:attribute name="tty" use="optional" default="false" type="xs:boolean" title=""/>
    <occi:attribute name="cpu_shares" use="optional" default="0" type="xs:integer" title="CPU shares for this Docker container"/>
    <occi:attribute name="pid" use="optional" type="xs:string" title="&apos;&apos; or &apos;host&apos;"/>
    <occi:attribute name="ipc" use="optional" type="xs:string" title="&apos;&apos;, &apos;host&apos; or &apos;container:[name:id]&apos;"/>
    <occi:attribute name="add_host" use="optional" type="xs:string" title=""/>
    <occi:attribute name="mac_address" use="optional" type="xs:string" title=""/>
    <occi:attribute name="rm" use="optional" type="xs:boolean" title=""/>
    <occi:attribute name="security_opt" use="optional" type="xs:string" title=""/>
    <occi:attribute name="device" use="optional" type="xs:string" title=""/>
    <occi:attribute name="lxc_conf" use="optional" type="xs:string" title=""/>
    <occi:attribute name="cpuset" use="optional" default="" type="xs:string" title=""/>
    <occi:attribute name="publish_all" use="optional" default="false" type="xs:boolean" title="Publish all exposed ports to random ports on the host interfaces"/>
    <occi:attribute name="read_only" use="optional" default="false" type="xs:boolean" title="Mount the container&apos;s root filesystem as read only"/>
    <occi:attribute name="monitored" use="optional" default="false" type="xs:boolean" title="This attribut allow us to monitor the container"/>
    <occi:attribute name="cpu_used" use="optional" type="xs:integer" title="CPU consumed by the conatiner"/>
    <occi:attribute name="memory_used" use="optional" type="xs:integer" title="Memory consumed by the container"/>
    <occi:attribute name="cpu_percent" use="optional" default="0" type="xs:string" title="The percentage of CPU used."/>
    <occi:attribute name="memory_percent" use="optional" default="0" type="xs:string" title="The percentage of Memory used."/>
    <occi:attribute name="disk_used" use="optional" type="xs:integer" title="The disk used."/>
    <occi:attribute name="disk_percent" use="optional" type="xs:string" title="The percentage of disk used."/>
    <occi:attribute name="bandwidth_used" use="optional" type="xs:integer" title="The bandwidth used by the container."/>
    <occi:attribute name="bandwidth_percent" use="optional" type="xs:string" title="The percentage of bandwith used."/>
    <occi:attribute name="monitoring_interval" use="optional" default="1000" type="xs:integer" title="The time interval in which the metrics are retrieved from container. This value is in milliseconds."/>
    <occi:attribute name="cpu_max_value" use="optional" default="" type="xs:integer" title="The CPU max value espression used by the Gauge."/>
    <occi:attribute name="memory_max_value" use="optional" type="xs:integer" title="The memory max value expression used by the gauge."/>
    <occi:attribute name="core_max" use="optional" default="1" type="xs:integer" title="The maximum number core availbale on the machine. This value is setting dynamically."/>
    <occi:action term="create" scheme="http://occiware.org/occi/docker/container/action#" title="">
    </occi:action>
    <occi:action term="start" scheme="http://occiware.org/occi/docker/container/action#" title="">
    </occi:action>
    <occi:action term="stop" scheme="http://occiware.org/occi/docker/container/action#" title="">
    </occi:action>
    <occi:action term="run" scheme="http://occiware.org/occi/docker/container/action#" title="">
    </occi:action>
    <occi:action term="pause" scheme="http://occiware.org/occi/docker/container/action#" title="">
    </occi:action>
    <occi:action term="unpause" scheme="http://occiware.org/occi/docker/container/action#" title="">
    </occi:action>
    <occi:action term="kill" scheme="http://occiware.org/occi/docker/container/action#" title="">
      <occi:attribute name="signal" use="required" default="KILL" type="xs:string" title=""/>
    </occi:action>
  </occi:kind>

  <!-- Kind: Link between containers -->
  <occi:kind term="link" scheme="http://occiware.org/occi/docker#" title="Link between containers">
    <occi:parent term="link" scheme="http://schemas.ogf.org/occi/core#"/>
    <occi:attribute name="alias" use="optional" type="xs:string" title="The alias of this Link instance"/>
  </occi:kind>

  <!-- Kind: VolumsFrom -->
  <occi:kind term="volumesfrom" scheme="http://occiware.org/occi/docker#" title="VolumsFrom">
    <occi:parent term="link" scheme="http://schemas.ogf.org/occi/core#"/>
    <occi:attribute name="mode" use="optional" default="read_write" type="xs:string" title="The mode of this VolumesFrom instance"/>
  </occi:kind>

  <!-- Kind:  -->
  <occi:kind term="contains" scheme="http://occiware.org/occi/docker#" title="">
    <occi:parent term="link" scheme="http://schemas.ogf.org/occi/core#"/>
  </occi:kind>

  <!-- Kind: Machine Resource -->
  <occi:kind term="machine" scheme="http://occiware.org/occi/docker#" title="Machine Resource">
    <occi:parent term="compute" scheme="http://schemas.ogf.org/occi/infrastructure#"/>
    <occi:attribute name="name" use="required" type="xs:string" title=""/>
  </occi:kind>

  <!-- Kind: Machine on Amazon EC2 -->
  <occi:kind term="machine_Amazon_EC2" scheme="http://occiware.org/occi/docker#" title="Machine on Amazon EC2">
    <occi:parent term="machine" scheme="http://occiware.org/occi/docker#"/>
    <occi:attribute name="access_key" use="required" type="xs:string" title="Your access key id for the Amazon Web Services API"/>
    <occi:attribute name="ami" use="optional" default="ami-4ae27e22" type="xs:string" title="The AMI ID of the instance to use"/>
    <occi:attribute name="instance_type" use="optional" default="t2.micro" type="xs:string" title="The instance type to run"/>
    <occi:attribute name="region" use="optional" default="us-east-1" type="xs:string" title="The region to use when launching the instance"/>
    <occi:attribute name="root_size" use="optional" default="16" type="xs:integer" title="The root disk size of the instance (in GB)"/>
    <occi:attribute name="secret_key" use="required" type="xs:string" title="Your secret access key for the Amazon Web Services API"/>
    <occi:attribute name="security_group" use="optional" default="docker-machine" type="xs:string" title="AWS VPC security group name"/>
    <occi:attribute name="session_token" use="optional" type="xs:string" title="Your session token for the Amazon Web Services API"/>
    <occi:attribute name="subnet_id" use="optional" type="xs:string" title="AWS VPC subnet id"/>
    <occi:attribute name="vpc_id" use="required" type="xs:string" title="Your VPC ID to launch the instance in"/>
    <occi:attribute name="zone" use="optional" default="a" type="xs:string" title="The AWS zone launch the instance in (i.e. one of a,b,c,d,e)"/>
  </occi:kind>

  <!-- Kind: Machine on Digital Ocean -->
  <occi:kind term="machine_Digital_Ocean" scheme="http://occiware.org/occi/docker#" title="Machine on Digital Ocean">
    <occi:parent term="machine" scheme="http://occiware.org/occi/docker#"/>
    <occi:attribute name="access_token" use="required" type="xs:string" title="Your personal access token for the Digital Ocean API"/>
    <occi:attribute name="image" use="optional" default="docker" type="xs:string" title="The name of the Digital Ocean image to use"/>
    <occi:attribute name="region" use="optional" default="nyc3" type="xs:string" title="The region to create the droplet in"/>
    <occi:attribute name="size" use="optional" default="512mb" type="xs:string" title="The size of the Digital Ocean driver (larger than default options are of the form 2gb)"/>
  </occi:kind>

  <!-- Kind: Machine on Google Compute Engine -->
  <occi:kind term="machine_Google_Compute_Engine" scheme="http://occiware.org/occi/docker#" title="Machine on Google Compute Engine">
    <occi:parent term="machine" scheme="http://occiware.org/occi/docker#"/>
    <occi:attribute name="zone" use="optional" default="us-central1-a" type="xs:string" title="The zone to launch the instance"/>
    <occi:attribute name="machine_type" use="optional" default="f1-micro" type="xs:string" title="The type of instance"/>
    <occi:attribute name="username" use="optional" default="docker-user" type="xs:string" title="The username to use for the instance"/>
    <occi:attribute name="instance_name" use="optional" default="docker-machine" type="xs:string" title="The name of the instance"/>
    <occi:attribute name="project" use="required" type="xs:string" title="The name of your project to use when launching the instance"/>
  </occi:kind>

  <!-- Kind: Machine on IBM SoftLayer -->
  <occi:kind term="machine_IBM_SoftLayer" scheme="http://occiware.org/occi/docker#" title="Machine on IBM SoftLayer">
    <occi:parent term="machine" scheme="http://occiware.org/occi/docker#"/>
    <occi:attribute name="api_endpoint" use="optional" type="xs:string" title="Change softlayer API endpoint"/>
    <occi:attribute name="user" use="required" type="xs:string" title="username for your softlayer account, api key needs to match this user"/>
    <occi:attribute name="api_key" use="required" type="xs:string" title="API key for your user account"/>
    <occi:attribute name="cpu" use="optional" type="xs:integer" title="Number of CPU&apos;s for the machine"/>
    <occi:attribute name="disk_size" use="optional" default="" type="xs:integer" title="Size of the disk in MB. 0 sets the softlayer default"/>
    <occi:attribute name="domain" use="required" type="xs:string" title="domain name for the machine"/>
    <occi:attribute name="hourly_billing" use="optional" default="true" type="xs:boolean" title="Sets the hourly billing flag (default), otherwise uses monthly billing"/>
    <occi:attribute name="image" use="optional" type="xs:string" title="OS Image to use"/>
    <occi:attribute name="local_disk" use="optional" type="xs:boolean" title="Use local machine disk instead of softlayer SAN"/>
    <occi:attribute name="private_net_only" use="optional" type="xs:boolean" title="Disable public networking"/>
    <occi:attribute name="region" use="optional" type="xs:string" title="softlayer region"/>
  </occi:kind>

  <!-- Kind: Machine on Microsoft Azure -->
  <occi:kind term="machine_Microsoft_Azure" scheme="http://occiware.org/occi/docker#" title="Machine on Microsoft Azure">
    <occi:parent term="machine" scheme="http://occiware.org/occi/docker#"/>
    <occi:attribute name="subscription_id" use="required" type="xs:string" title="Your Azure subscription ID (A GUID like d255d8d7-5af0-4f5c-8a3e-1545044b861e)"/>
    <occi:attribute name="subscription_cert" use="required" type="xs:string" title="Your Azure subscription cert"/>
  </occi:kind>

  <!-- Kind: Machine on Microsoft Hyper-V -->
  <occi:kind term="machine_Microsoft_Hyper_V" scheme="http://occiware.org/occi/docker#" title="Machine on Microsoft Hyper-V">
    <occi:parent term="machine" scheme="http://occiware.org/occi/docker#"/>
    <occi:attribute name="boot2docker_location" use="optional" type="xs:string" title="Location of a local boot2docker iso to use. Overrides the URL option below"/>
    <occi:attribute name="boot2docker_url" use="optional" type="xs:string" title="The URL of the boot2docker iso. Defaults to the latest available version"/>
    <occi:attribute name="disk_size" use="optional" default="20000" type="xs:integer" title="Size of disk for the host in MB"/>
    <occi:attribute name="virtual_switch" use="optional" type="xs:string" title="Name of the virtual switch to use. Defaults to first found"/>
  </occi:kind>

  <!-- Kind: Machine on OpenStack -->
  <occi:kind term="machine_OpenStack" scheme="http://occiware.org/occi/docker#" title="Machine on OpenStack">
    <occi:parent term="machine" scheme="http://occiware.org/occi/docker#"/>
    <occi:attribute name="flavor_id" use="required" type="xs:string" title="The flavor ID to use when creating the machine"/>
    <occi:attribute name="image_id" use="required" type="xs:string" title="The image ID to use when creating the machine"/>
    <occi:attribute name="auth_url" use="optional" type="xs:string" title="Keystone service base URL"/>
    <occi:attribute name="username" use="optional" type="xs:string" title="User identifer to authenticate with"/>
    <occi:attribute name="password" use="optional" type="xs:string" title="User password. It can be omitted if the standard environment variable OS_PASSWORD is set."/>
    <occi:attribute name="tenant_name" use="optional" type="xs:string" title="Identify the tenant in which the machine will be created"/>
    <occi:attribute name="tenant_id" use="optional" type="xs:string" title="Identify the tenant in which the machine will be created"/>
    <occi:attribute name="region" use="optional" type="xs:string" title="The region to work on. Can be omitted if there is only one region on the OpenStack"/>
    <occi:attribute name="endpoint_type" use="optional" type="xs:string" title="Endpoint type can be internalURL, adminURL on publicURL. If is a helper for the driver to choose the right URL in the OpenStack service catalog. If not provided the default id publicURL"/>
    <occi:attribute name="net_id" use="optional" type="xs:string" title="The private network id the machine will be connected on. If your OpenStack project project contains only one private network it will be use automatically"/>
    <occi:attribute name="sec_groups" use="optional" type="xs:string" title="If security groups are available on your OpenStack you can specify a comma separated list to use for the machine (e.g. secgrp001,secgrp002)"/>
    <occi:attribute name="floatingip_pool" use="optional" type="xs:string" title="The IP pool that will be used to get a public IP an assign it to the machine. If there is an IP address already allocated but not assigned to any machine, this IP will be chosen and assigned to the machine. If there is no IP address already allocated a new IP will be allocated and assigned to the machine"/>
  </occi:kind>

  <!-- Kind: Machine on Rackspace cloud -->
  <occi:kind term="machine_Rackspace" scheme="http://occiware.org/occi/docker#" title="Machine on Rackspace cloud">
    <occi:parent term="machine" scheme="http://occiware.org/occi/docker#"/>
    <occi:attribute name="username" use="required" type="xs:string" title="Rackspace account username"/>
    <occi:attribute name="api_key" use="required" type="xs:string" title="Rackspace API key"/>
    <occi:attribute name="region" use="required" type="xs:string" title="Rackspace region name"/>
    <occi:attribute name="endpoint_type" use="optional" default="publicURL" type="xs:string" title="Rackspace endpoint type (adminURL, internalURL or the default publicURL)"/>
    <occi:attribute name="image_id" use="optional" default="Ubuntu 14.10 (Utopic Unicorn) (PVHVM)" type="xs:string" title="Rackspace image ID "/>
    <occi:attribute name="flavor_id" use="optional" default="General Purpose 1GB" type="xs:string" title="Rackspace flavor ID"/>
    <occi:attribute name="ssh_user" use="optional" default="root" type="xs:string" title="SSH user for the newly booted machine"/>
    <occi:attribute name="ssh_port" use="optional" default="22" type="xs:integer" title="SSH port for the newly booted machine"/>
  </occi:kind>

  <!-- Kind: Machine on VirtualBox -->
  <occi:kind term="machine_VirtualBox" scheme="http://occiware.org/occi/docker#" title="Machine on VirtualBox">
    <occi:parent term="machine" scheme="http://occiware.org/occi/docker#"/>
    <occi:attribute name="boot2docker_url" use="optional" type="xs:string" title="The URL of the boot2docker image. Default to the latest available version"/>
    <occi:attribute name="disk_size" use="optional" default="20000" type="xs:integer" title="Size of disk for the host in MB"/>
  </occi:kind>

  <!-- Kind: Machine on VMware Fusion -->
  <occi:kind term="machine_VMware_Fusion" scheme="http://occiware.org/occi/docker#" title="Machine on VMware Fusion">
    <occi:parent term="machine" scheme="http://occiware.org/occi/docker#"/>
    <occi:attribute name="boot2docker_url" use="optional" type="xs:string" title="URL for boot2docker image"/>
    <occi:attribute name="disk_size" use="optional" default="20000" type="xs:integer" title="Size of disk for host VM (in MB)"/>
    <occi:attribute name="memory_size" use="optional" default="1024" type="xs:integer" title="Size of memory for host VM (in MB)"/>
  </occi:kind>

  <!-- Kind: Machine on VMware vCloud Air -->
  <occi:kind term="machine_VMware_vCloud_Air" scheme="http://occiware.org/occi/docker#" title="Machine on VMware vCloud Air">
    <occi:parent term="machine" scheme="http://occiware.org/occi/docker#"/>
    <occi:attribute name="username" use="required" type="xs:string" title="vCloud Air Username"/>
    <occi:attribute name="password" use="required" type="xs:string" title="vCloud Air Password"/>
    <occi:attribute name="catalog" use="optional" default="Public Catalog" type="xs:string" title="Catalog "/>
    <occi:attribute name="catalogitem" use="optional" default="Ubuntu Server 12.04 LTS (amd64 20140927)" type="xs:string" title="Catalog Item "/>
    <occi:attribute name="computeid" use="optional" type="xs:string" title="Compute ID (if using Dedicated Cloud)"/>
    <occi:attribute name="cpu_count" use="optional" default="1" type="xs:integer" title="VM Cpu Count"/>
    <occi:attribute name="docker_port" use="optional" default="2376" type="xs:integer" title="Docker port "/>
    <occi:attribute name="edgegateway" use="optional" default="&lt;vdcid&gt;" type="xs:string" title="Organization Edge Gateway"/>
    <occi:attribute name="memory_size" use="optional" default="2048" type="xs:integer" title="VM Memory Size in MB"/>
    <occi:attribute name="vapp_name" use="optional" default="&lt;autogenerated&gt;" type="xs:string" title="vApp Name"/>
    <occi:attribute name="orgvdcnetwork" use="optional" default="&lt;vdcid&gt;-default-routed" type="xs:string" title="Organization VDC Network to attach"/>
    <occi:attribute name="provision" use="optional" default="true" type="xs:boolean" title="Install Docker binaries"/>
    <occi:attribute name="publicip" use="optional" type="xs:string" title="Org Public IP to use"/>
    <occi:attribute name="ssh_port" use="optional" default="22" type="xs:integer" title="SSH port"/>
    <occi:attribute name="vdcid" use="optional" type="xs:string" title="Virtual Data Center ID"/>
  </occi:kind>

  <!-- Kind: Machine on VMware vSphere -->
  <occi:kind term="machine_VMware_vSphere" scheme="http://occiware.org/occi/docker#" title="Machine on VMware vSphere">
    <occi:parent term="machine" scheme="http://occiware.org/occi/docker#"/>
    <occi:attribute name="username" use="required" type="xs:string" title="vSphere Username"/>
    <occi:attribute name="password" use="required" type="xs:string" title="vSphere Password"/>
    <occi:attribute name="boot2docker_url" use="required" type="xs:string" title="URL for boot2docker image"/>
    <occi:attribute name="compute_ip" use="optional" type="xs:string" title="Compute host IP where the Docker VM will be instantiated"/>
    <occi:attribute name="cpu_count" use="optional" default="2" type="xs:integer" title="CPU number for Docker VM"/>
    <occi:attribute name="datacenter" use="optional" type="xs:string" title="Datacenter for Docker VM (must be set to ha-datacenter when connecting to a single host)"/>
    <occi:attribute name="datastore" use="optional" type="xs:string" title="Datastore for Docker VM"/>
    <occi:attribute name="disk_size" use="optional" default="20000" type="xs:integer" title="Size of disk for Docker VM (in MB)"/>
    <occi:attribute name="memory_size" use="optional" default="2048" type="xs:integer" title="Size of memory for Docker VM (in MB) "/>
    <occi:attribute name="network" use="optional" type="xs:string" title="Network where the Docker VM will be attached"/>
    <occi:attribute name="pool" use="optional" type="xs:string" title="Resource pool for Docker VM"/>
    <occi:attribute name="vcenter" use="optional" type="xs:string" title=" IP/hostname for vCenter (or ESXi if connecting directly to a single host)"/>
  </occi:kind>

</occi:extension>
